<?xml version="1.0"?>
<gsmrs version="2.0" sport="soccer" lang="en" last_generated="2013-02-03 03:46:25"><method method_id="35" name="get_match_extra"><parameter name="id" value="1293741"/><parameter name="lang" value="en"/></method><competition competition_id="8" name="Premier League" teamtype="default" display_order="10" type="club" area_id="68" area_name="England" last_updated="2013-02-02 20:41:05" soccertype="default"><season season_id="7185" name="2012/2013" start_date="2012-08-18" end_date="2013-05-30" service_level="0" last_updated="2013-02-02 20:41:05"><round round_id="17950" name="Regular Season" start_date="2012-08-14" end_date="2013-05-30" type="table" groups="0" has_outgroup_matches="no" last_updated="2013-02-02 20:41:05"><match match_id="1293741" date_utc="2012-10-06" time_utc="14:00:00" date_london="2012-10-06" time_london="15:00:00" team_A_id="661" team_A_name="Chelsea" team_A_country="ENG" team_B_id="677" team_B_name="Norwich City" team_B_country="ENG" status="Played" gameweek="7" winner="team_A" fs_A="4" fs_B="1" hts_A="3" hts_B="1" ets_A="" ets_B="" ps_A="" ps_B="" last_updated="2012-10-06 18:01:51"><matchinfo><venue venue_id="83" name="Stamford Bridge" city="London" area_id="68"/><referee person_id="60851" name="A. Taylor"/><assistant_referee person_id="92631" name="A. Halliday"/><assistant_referee person_id="83465" name="S. Beck"/><fourth_official person_id="59694" name="M. Halsey"/><attendance value="41784"/><formation team_A="4-5-1" team_B="4-5-1"/></matchinfo><lineups><event event_id="9370070" code="L" name="Line-up" person="P. &#x10C;ech" person_id="237" team_id="661" minute="0" minute_extra="" last_updated="2012-10-06 15:14:07"><pitch_position position_x="GK" position_y="C"/></event><event event_id="9370071" code="L" name="Line-up" person="B. Ivanovi&#x107;" person_id="6456" team_id="661" minute="0" minute_extra="" last_updated="2012-10-06 15:14:07"><pitch_position position_x="D2" position_y="R"/></event><event event_id="9370072" code="L" name="Line-up" person="A. Cole" person_id="178" team_id="661" minute="0" minute_extra="" last_updated="2012-10-06 15:14:07"><pitch_position position_x="D2" position_y="L"/></event><event event_id="9370073" code="L" name="Line-up" person="David Luiz" person_id="16580" team_id="661" minute="0" minute_extra="" last_updated="2012-10-06 15:14:07"><pitch_position position_x="D2" position_y="CL"/></event><event event_id="9370080" code="L" name="Line-up" person="J. Terry" person_id="181" team_id="661" minute="0" minute_extra="" last_updated="2012-10-06 15:14:07"><pitch_position position_x="D2" position_y="CR"/></event><event event_id="9370074" code="L" name="Line-up" person="F. Lampard" person_id="189" team_id="661" minute="0" minute_extra="" last_updated="2012-10-06 15:14:07"><pitch_position position_x="M" position_y="CL"/></event><event event_id="9370077" code="L" name="Line-up" person="Oscar" person_id="57860" team_id="661" minute="0" minute_extra="" last_updated="2012-10-06 15:14:07"><pitch_position position_x="AM" position_y="C"/></event><event event_id="9370078" code="L" name="Line-up" person="J. Obi Mikel" person_id="2536" team_id="661" minute="0" minute_extra="" last_updated="2012-10-06 15:14:07"><pitch_position position_x="M" position_y="CR"/></event><event event_id="9370079" code="L" name="Line-up" person="E. Hazard" person_id="39358" team_id="661" minute="0" minute_extra="" last_updated="2012-10-06 15:14:07"><pitch_position position_x="AM" position_y="L"/></event><event event_id="9370075" code="L" name="Line-up" person="Fernando Torres" person_id="334" team_id="661" minute="0" minute_extra="" last_updated="2012-10-06 15:14:07"><pitch_position position_x="A" position_y="C"/></event><event event_id="9370076" code="L" name="Line-up" person="Mata" person_id="19106" team_id="661" minute="0" minute_extra="" last_updated="2012-10-06 15:14:07"><pitch_position position_x="AM" position_y="R"/></event><event event_id="9370851" code="L" name="Line-up" person="J. Ruddy" person_id="2867" team_id="677" minute="0" minute_extra="" last_updated="2012-10-06 15:35:43"><pitch_position position_x="GK" position_y="C"/></event><event event_id="9370852" code="L" name="Line-up" person="R. Martin" person_id="51076" team_id="677" minute="0" minute_extra="" last_updated="2012-10-06 15:35:43"><pitch_position position_x="D2" position_y="R"/></event><event event_id="9370854" code="L" name="Line-up" person="S. Bassong" person_id="20944" team_id="677" minute="0" minute_extra="" last_updated="2012-10-06 15:35:43"><pitch_position position_x="D2" position_y="CL"/></event><event event_id="9370864" code="L" name="Line-up" person="Garrido" person_id="3233" team_id="677" minute="0" minute_extra="" last_updated="2012-10-06 15:35:43"><pitch_position position_x="D2" position_y="L"/></event><event event_id="9370865" code="L" name="Line-up" person="L. Barnett" person_id="15440" team_id="677" minute="0" minute_extra="" last_updated="2012-10-06 15:35:43"><pitch_position position_x="D2" position_y="CR"/></event><event event_id="9370853" code="L" name="Line-up" person="B. Johnson" person_id="53098" team_id="677" minute="0" minute_extra="" last_updated="2012-10-06 15:35:43"><pitch_position position_x="M" position_y="CL"/></event><event event_id="9370857" code="L" name="Line-up" person="J. Howson" person_id="53096" team_id="677" minute="0" minute_extra="" last_updated="2012-10-06 15:35:43"><pitch_position position_x="M" position_y="CR"/></event><event event_id="9370861" code="L" name="Line-up" person="W. Hoolahan" person_id="15954" team_id="677" minute="0" minute_extra="" last_updated="2012-10-06 15:35:43"><pitch_position position_x="AM" position_y="CR"/></event><event event_id="9370863" code="L" name="Line-up" person="E. Bennett" person_id="50442" team_id="677" minute="0" minute_extra="" last_updated="2012-10-06 15:35:43"><pitch_position position_x="M" position_y="R"/></event><event event_id="9370867" code="L" name="Line-up" person="A. Tettey" person_id="7909" team_id="677" minute="0" minute_extra="" last_updated="2012-10-06 15:35:44"><pitch_position position_x="M" position_y="L"/></event><event event_id="9370858" code="L" name="Line-up" person="G. Holt" person_id="50760" team_id="677" minute="0" minute_extra="" last_updated="2012-10-06 15:35:43"><pitch_position position_x="A" position_y="CL"/></event></lineups><goals><goal><event event_id="9372739" code="G" name="Goal" person="G. Holt" person_id="50760" team_id="677" minute="11" minute_extra="" last_updated="2012-10-06 16:11:39"><goal_extra type="" distance="" field_side="" net_part=""/></event><event event_id="9372771" code="AS" name="Assist" person="L. Barnett" person_id="15440" team_id="677" minute="11" minute_extra="" last_updated="2012-10-06 16:13:22"/></goal><goal><event event_id="9372847" code="G" name="Goal" person="Fernando Torres" person_id="334" team_id="661" minute="14" minute_extra="" last_updated="2012-10-06 16:14:49"><goal_extra type="" distance="" field_side="" net_part=""/></event><event event_id="9372861" code="AS" name="Assist" person="B. Ivanovi&#x107;" person_id="6456" team_id="661" minute="14" minute_extra="" last_updated="2012-10-06 16:14:49"/></goal><goal><event event_id="9372994" code="G" name="Goal" person="F. Lampard" person_id="189" team_id="661" minute="22" minute_extra="" last_updated="2012-10-06 16:22:00"><goal_extra type="" distance="" field_side="" net_part=""/></event></goal><goal><event event_id="9373200" code="G" name="Goal" person="E. Hazard" person_id="39358" team_id="661" minute="31" minute_extra="" last_updated="2012-10-06 16:30:57"><goal_extra type="" distance="" field_side="" net_part=""/></event><event event_id="9373202" code="AS" name="Assist" person="Mata" person_id="19106" team_id="661" minute="31" minute_extra="" last_updated="2012-10-06 16:30:57"/></goal><goal><event event_id="9374247" code="G" name="Goal" person="B. Ivanovi&#x107;" person_id="6456" team_id="661" minute="76" minute_extra="" last_updated="2012-10-06 17:32:40"><goal_extra type="" distance="" field_side="" net_part=""/></event><event event_id="9374251" code="AS" name="Assist" person="Mata" person_id="19106" team_id="661" minute="76" minute_extra="" last_updated="2012-10-06 17:32:40"/></goal></goals><bookings/></match></round></season></competition></gsmrs>
