<?xml version="1.0"?>
<gsmrs version="2.0" sport="soccer" lang="en" last_generated="2013-02-03 03:46:16"><method method_id="35" name="get_match_extra"><parameter name="id" value="1293704"/><parameter name="lang" value="en"/></method><competition competition_id="8" name="Premier League" teamtype="default" display_order="10" type="club" area_id="68" area_name="England" last_updated="2013-02-02 20:41:05" soccertype="default"><season season_id="7185" name="2012/2013" start_date="2012-08-18" end_date="2013-05-30" service_level="0" last_updated="2013-02-02 20:41:05"><round round_id="17950" name="Regular Season" start_date="2012-08-14" end_date="2013-05-30" type="table" groups="0" has_outgroup_matches="no" last_updated="2013-02-02 20:41:05"><match match_id="1293704" date_utc="2012-09-02" time_utc="15:00:00" date_london="2012-09-02" time_london="16:00:00" team_A_id="664" team_A_name="Newcastle United" team_A_country="ENG" team_B_id="665" team_B_name="Aston Villa" team_B_country="ENG" status="Played" gameweek="3" winner="draw" fs_A="1" fs_B="1" hts_A="0" hts_B="1" ets_A="" ets_B="" ps_A="" ps_B="" last_updated="2012-09-02 19:00:13"><matchinfo><venue venue_id="92" name="St. James' Park" city="Newcastle-upon-Tyne" area_id="68"/><referee person_id="60422" name="L. Probert"/><assistant_referee person_id="83465" name="S. Beck"/><assistant_referee person_id="56448" name="S. Bennett"/><fourth_official person_id="59690" name="K. Friend"/><attendance value="48245"/><formation team_A="4-4-2" team_B="4-4-2"/></matchinfo><lineups><event event_id="8945951" code="L" name="Line-up" person="T. Krul" person_id="5256" team_id="664" minute="0" minute_extra="" last_updated="2012-09-02 16:30:43"><pitch_position position_x="GK" position_y="C"/></event><event event_id="8945952" code="L" name="Line-up" person="F. Coloccini" person_id="105" team_id="664" minute="0" minute_extra="" last_updated="2012-09-02 16:30:43"><pitch_position position_x="D1" position_y="CL"/></event><event event_id="8945953" code="L" name="Line-up" person="D. Santon" person_id="61131" team_id="664" minute="0" minute_extra="" last_updated="2012-09-02 16:30:44"><pitch_position position_x="D2" position_y="L"/></event><event event_id="8945955" code="L" name="Line-up" person="D. Simpson" person_id="20278" team_id="664" minute="0" minute_extra="" last_updated="2012-09-02 16:30:44"><pitch_position position_x="D2" position_y="R"/></event><event event_id="8945967" code="L" name="Line-up" person="S. Taylor" person_id="2892" team_id="664" minute="0" minute_extra="" last_updated="2012-09-02 16:30:44"><pitch_position position_x="D1" position_y="CR"/></event><event event_id="8945954" code="L" name="Line-up" person="Y. Cabaye" person_id="2056" team_id="664" minute="0" minute_extra="" last_updated="2012-09-02 16:30:44"><pitch_position position_x="M" position_y="CL"/></event><event event_id="8945957" code="L" name="Line-up" person="V. Anita" person_id="24607" team_id="664" minute="0" minute_extra="" last_updated="2012-09-02 16:30:44"><pitch_position position_x="M" position_y="CR"/></event><event event_id="8945959" code="L" name="Line-up" person="H. Ben Arfa" person_id="1588" team_id="664" minute="0" minute_extra="" last_updated="2012-09-02 16:30:44"><pitch_position position_x="M" position_y="R"/></event><event event_id="8945962" code="L" name="Line-up" person="J. Guti&#xE9;rrez" person_id="3206" team_id="664" minute="0" minute_extra="" last_updated="2012-09-02 16:30:44"><pitch_position position_x="M" position_y="L"/></event><event event_id="8945958" code="L" name="Line-up" person="P. Ciss&#xE9;" person_id="37915" team_id="664" minute="0" minute_extra="" last_updated="2012-09-02 16:30:44"><pitch_position position_x="A" position_y="CL"/></event><event event_id="8945963" code="L" name="Line-up" person="D. Ba" person_id="13192" team_id="664" minute="0" minute_extra="" last_updated="2012-09-02 16:30:44"><pitch_position position_x="A" position_y="CR"/></event><event event_id="8946011" code="L" name="Line-up" person="B. Guzan" person_id="6912" team_id="665" minute="0" minute_extra="" last_updated="2012-09-02 16:31:24"><pitch_position position_x="GK" position_y="C"/></event><event event_id="8946003" code="L" name="Line-up" person="R. Vlaar" person_id="2248" team_id="665" minute="0" minute_extra="" last_updated="2012-09-02 16:31:24"><pitch_position position_x="D1" position_y="CR"/></event><event event_id="8946004" code="L" name="Line-up" person="C. Clark" person_id="89489" team_id="665" minute="0" minute_extra="" last_updated="2012-09-02 16:31:24"><pitch_position position_x="D1" position_y="CL"/></event><event event_id="8946014" code="L" name="Line-up" person="E. Lichaj" person_id="90118" team_id="665" minute="0" minute_extra="" last_updated="2012-09-02 16:31:24"><pitch_position position_x="D2" position_y="L"/></event><event event_id="8946016" code="L" name="Line-up" person="M. Lowton" person_id="85440" team_id="665" minute="0" minute_extra="" last_updated="2012-09-02 16:31:24"><pitch_position position_x="D2" position_y="R"/></event><event event_id="8946005" code="L" name="Line-up" person="S. Ireland" person_id="2854" team_id="665" minute="0" minute_extra="" last_updated="2012-09-02 16:31:24"><pitch_position position_x="M" position_y="CL"/></event><event event_id="8946006" code="L" name="Line-up" person="K. El Ahmadi" person_id="2466" team_id="665" minute="0" minute_extra="" last_updated="2012-09-02 16:31:24"><pitch_position position_x="M" position_y="CR"/></event><event event_id="8946010" code="L" name="Line-up" person="B. Holman" person_id="2372" team_id="665" minute="0" minute_extra="" last_updated="2012-09-02 16:31:24"><pitch_position position_x="M" position_y="L"/></event><event event_id="8946012" code="L" name="Line-up" person="B. Bannan" person_id="47910" team_id="665" minute="0" minute_extra="" last_updated="2012-09-02 16:31:24"><pitch_position position_x="M" position_y="R"/></event><event event_id="8946007" code="L" name="Line-up" person="D. Bent" person_id="2784" team_id="665" minute="0" minute_extra="" last_updated="2012-09-02 16:31:24"><pitch_position position_x="A" position_y="CL"/></event><event event_id="8946013" code="L" name="Line-up" person="A. Weimann" person_id="89062" team_id="665" minute="0" minute_extra="" last_updated="2012-09-02 16:31:24"><pitch_position position_x="A" position_y="CR"/></event></lineups><goals><goal><event event_id="8947623" code="G" name="Goal" person="C. Clark" person_id="89489" team_id="665" minute="22" minute_extra="" last_updated="2012-09-02 17:22:20"><goal_extra type="" distance="" field_side="" net_part=""/></event><event event_id="8947624" code="AS" name="Assist" person="B. Bannan" person_id="47910" team_id="665" minute="22" minute_extra="" last_updated="2012-09-02 17:22:20"/></goal><goal><event event_id="8949014" code="G" name="Goal" person="H. Ben Arfa" person_id="1588" team_id="664" minute="59" minute_extra="" last_updated="2012-09-02 18:20:50"><goal_extra type="" distance="" field_side="" net_part=""/></event></goal></goals><bookings><event event_id="8947764" code="YC" name="Yellow card" person="K. El Ahmadi" person_id="2466" team_id="665" minute="27" minute_extra="" last_updated="2012-09-02 17:26:43"><booking_extra reason=""/></event><event event_id="8949707" code="YC" name="Yellow card" person="J. Guti&#xE9;rrez" person_id="3206" team_id="664" minute="85" minute_extra="" last_updated="2012-09-02 18:46:52"><booking_extra reason=""/></event><event event_id="8949794" code="YC" name="Yellow card" person="E. Lichaj" person_id="90118" team_id="665" minute="90" minute_extra="" last_updated="2012-09-02 18:51:36"><booking_extra reason=""/></event><event event_id="8949831" code="YC" name="Yellow card" person="B. Guzan" person_id="6912" team_id="665" minute="90" minute_extra="1" last_updated="2012-09-02 18:53:23"><booking_extra reason=""/></event><event event_id="8949855" code="YC" name="Yellow card" person="B. Holman" person_id="2372" team_id="665" minute="90" minute_extra="4" last_updated="2012-09-02 18:55:14"><booking_extra reason=""/></event></bookings></match></round></season></competition></gsmrs>
