<?xml version="1.0"?>
<gsmrs version="2.0" sport="soccer" lang="en" last_generated="2013-02-03 03:46:46"><method method_id="35" name="get_match_extra"><parameter name="id" value="1293817"/><parameter name="lang" value="en"/></method><competition competition_id="8" name="Premier League" teamtype="default" display_order="10" type="club" area_id="68" area_name="England" last_updated="2013-02-02 20:41:05" soccertype="default"><season season_id="7185" name="2012/2013" start_date="2012-08-18" end_date="2013-05-30" service_level="0" last_updated="2013-02-02 20:41:05"><round round_id="17950" name="Regular Season" start_date="2012-08-14" end_date="2013-05-30" type="table" groups="0" has_outgroup_matches="no" last_updated="2013-02-02 20:41:05"><match match_id="1293817" date_utc="2012-11-28" time_utc="19:45:00" date_london="2012-11-28" time_london="19:45:00" team_A_id="675" team_A_name="Tottenham Hotspur" team_A_country="ENG" team_B_id="663" team_B_name="Liverpool" team_B_country="ENG" status="Played" gameweek="14" winner="team_A" fs_A="2" fs_B="1" hts_A="2" hts_B="0" ets_A="" ets_B="" ps_A="" ps_B="" last_updated="2012-11-28 22:46:01"><matchinfo><venue venue_id="91" name="White Hart Lane" city="London" area_id="68"/><referee person_id="56450" name="P. Dowd"/><assistant_referee person_id="91498" name="S. Burt"/><assistant_referee person_id="199433" name="J. Brooks"/><fourth_official person_id="60873" name="G. Ward"/><attendance value="36162"/><formation team_A="4-5-1" team_B="4-5-1"/></matchinfo><lineups><event event_id="10030254" code="L" name="Line-up" person="Pepe Reina" person_id="318" team_id="663" minute="0" minute_extra="" last_updated="2012-11-28 20:00:00"><pitch_position position_x="GK" position_y="C"/></event><event event_id="10030246" code="L" name="Line-up" person="G. Johnson" person_id="2641" team_id="663" minute="0" minute_extra="" last_updated="2012-11-28 19:59:59"><pitch_position position_x="D2" position_y="R"/></event><event event_id="10030247" code="L" name="Line-up" person="Jos&#xE9; Enrique" person_id="16058" team_id="663" minute="0" minute_extra="" last_updated="2012-11-28 20:00:00"><pitch_position position_x="AM" position_y="L"/></event><event event_id="10030248" code="L" name="Line-up" person="D. Agger" person_id="2968" team_id="663" minute="0" minute_extra="" last_updated="2012-11-28 20:00:00"><pitch_position position_x="D2" position_y="CL"/></event><event event_id="10030256" code="L" name="Line-up" person="M. &#x160;krtel" person_id="5940" team_id="663" minute="0" minute_extra="" last_updated="2012-11-28 20:00:00"><pitch_position position_x="D2" position_y="CR"/></event><event event_id="10030250" code="L" name="Line-up" person="S. Gerrard" person_id="186" team_id="663" minute="0" minute_extra="" last_updated="2012-11-28 20:00:00"><pitch_position position_x="M" position_y="CR"/></event><event event_id="10030251" code="L" name="Line-up" person="J. Henderson" person_id="48010" team_id="663" minute="0" minute_extra="" last_updated="2012-11-28 20:00:00"><pitch_position position_x="M" position_y="CL"/></event><event event_id="10030252" code="L" name="Line-up" person="S. Downing" person_id="185" team_id="663" minute="0" minute_extra="" last_updated="2012-11-28 20:00:00"><pitch_position position_x="D2" position_y="L"/></event><event event_id="10030253" code="L" name="Line-up" person="J. Allen" person_id="47573" team_id="663" minute="0" minute_extra="" last_updated="2012-11-28 20:00:00"><pitch_position position_x="DM" position_y="C"/></event><event event_id="10030255" code="L" name="Line-up" person="R. Sterling" person_id="160414" team_id="663" minute="0" minute_extra="" last_updated="2012-11-28 20:00:00"><pitch_position position_x="AM" position_y="R"/></event><event event_id="10030249" code="L" name="Line-up" person="L. Su&#xE1;rez" person_id="2290" team_id="663" minute="0" minute_extra="" last_updated="2012-11-28 20:00:00"><pitch_position position_x="A" position_y="C"/></event><event event_id="10030284" code="L" name="Line-up" person="H. Lloris" person_id="1255" team_id="675" minute="0" minute_extra="" last_updated="2012-11-28 20:02:16"><pitch_position position_x="GK" position_y="C"/></event><event event_id="10030277" code="L" name="Line-up" person="J. Vertonghen" person_id="2190" team_id="675" minute="0" minute_extra="" last_updated="2012-11-28 20:02:16"><pitch_position position_x="D2" position_y="L"/></event><event event_id="10030280" code="L" name="Line-up" person="W. Gallas" person_id="538" team_id="675" minute="0" minute_extra="" last_updated="2012-11-28 20:02:16"><pitch_position position_x="D2" position_y="CL"/></event><event event_id="10030283" code="L" name="Line-up" person="M. Dawson" person_id="2932" team_id="675" minute="0" minute_extra="" last_updated="2012-11-28 20:02:16"><pitch_position position_x="D2" position_y="CR"/></event><event event_id="10030285" code="L" name="Line-up" person="K. Walker" person_id="68532" team_id="675" minute="0" minute_extra="" last_updated="2012-11-28 20:02:16"><pitch_position position_x="D2" position_y="R"/></event><event event_id="10030276" code="L" name="Line-up" person="C. Dempsey" person_id="664" team_id="675" minute="0" minute_extra="" last_updated="2012-11-28 20:02:16"><pitch_position position_x="M" position_y="C"/></event><event event_id="10030278" code="L" name="Line-up" person="A. Lennon" person_id="190" team_id="675" minute="0" minute_extra="" last_updated="2012-11-28 20:02:16"><pitch_position position_x="AM" position_y="R"/></event><event event_id="10030279" code="L" name="Line-up" person="G. Bale" person_id="15482" team_id="675" minute="0" minute_extra="" last_updated="2012-11-28 20:02:16"><pitch_position position_x="AM" position_y="L"/></event><event event_id="10030282" code="L" name="Line-up" person="M. Demb&#xE9;l&#xE9;" person_id="2197" team_id="675" minute="0" minute_extra="" last_updated="2012-11-28 20:02:16"><pitch_position position_x="DM" position_y="CR"/></event><event event_id="10030286" code="L" name="Line-up" person="Sandro" person_id="65306" team_id="675" minute="0" minute_extra="" last_updated="2012-11-28 20:02:16"><pitch_position position_x="DM" position_y="CL"/></event><event event_id="10030281" code="L" name="Line-up" person="J. Defoe" person_id="2950" team_id="675" minute="0" minute_extra="" last_updated="2012-11-28 20:02:16"><pitch_position position_x="A" position_y="C"/></event></lineups><goals><goal><event event_id="10031036" code="G" name="Goal" person="A. Lennon" person_id="190" team_id="675" minute="7" minute_extra="" last_updated="2012-11-28 20:53:16"><goal_extra type="" distance="" field_side="" net_part=""/></event><event event_id="10031038" code="AS" name="Assist" person="G. Bale" person_id="15482" team_id="675" minute="7" minute_extra="" last_updated="2012-11-28 20:53:16"/></goal><goal><event event_id="10031090" code="G" name="Goal" person="G. Bale" person_id="15482" team_id="675" minute="16" minute_extra="" last_updated="2012-11-28 21:01:22"><goal_extra type="" distance="" field_side="" net_part=""/></event></goal><goal><event event_id="10031533" code="OG" name="Own goal" person="G. Bale" person_id="15482" team_id="675" minute="72" minute_extra="" last_updated="2012-11-28 22:15:56"><goal_extra type="" distance="" field_side="" net_part=""/></event></goal></goals><bookings><event event_id="10031228" code="YC" name="Yellow card" person="M. &#x160;krtel" person_id="5940" team_id="663" minute="38" minute_extra="" last_updated="2012-11-28 21:23:15"><booking_extra reason=""/></event><event event_id="10031561" code="YC" name="Yellow card" person="G. Bale" person_id="15482" team_id="675" minute="78" minute_extra="" last_updated="2012-11-28 22:21:44"><booking_extra reason=""/></event><event event_id="10031654" code="YC" name="Yellow card" person="Jos&#xE9; Enrique" person_id="16058" team_id="663" minute="90" minute_extra="" last_updated="2012-11-28 22:34:53"><booking_extra reason=""/></event></bookings></match></round></season></competition></gsmrs>
